<Properties StartupConfiguration="{F33D6EDF-FAF1-4D2D-93E6-60993DF4540D}|Default">
  <MonoDevelop.Ide.Workbench ActiveDocument="SerkoTest/Models/TextDetail.cs">
    <Files>
      <File FileName="SerkoTest/Controllers/ValuesController.cs" Line="26" Column="1" />
      <File FileName="SerkoTest/appsettings.json" Line="1" Column="1" />
      <File FileName="SerkoTest/Controllers/ExtractDataController.cs" Line="71" Column="18" />
      <File FileName="SerkoTest/Program.cs" Line="17" Column="1" />
      <File FileName="SerkoTest/Models/Expense.cs" Line="23" Column="9" />
      <File FileName="SerkoTest/Services/IExtractDataServices.cs" Line="13" Column="15" />
      <File FileName="SerkoTest/Services/ExtractDataServices.cs" Line="64" Column="9" />
      <File FileName="SerkoTest/Models/Message.cs" Line="5" Column="6" />
      <File FileName="SerkoTest/Models/TextDetail.cs" Line="12" Column="31" />
    </Files>
  </MonoDevelop.Ide.Workbench>
  <MonoDevelop.Ide.Workspace ActiveConfiguration="Debug" />
  <MonoDevelop.Ide.DebuggingService.Breakpoints>
    <BreakpointStore />
  </MonoDevelop.Ide.DebuggingService.Breakpoints>
  <MonoDevelop.Ide.DebuggingService.PinnedWatches />
  <MultiItemStartupConfigurations />
  <MonoDevelop.Ide.ItemProperties.SerkoTest PreferredExecutionTarget="MonoDevelop.Default" />
</Properties>